{
  "branch": "master",
  "files": [
    "main.md"
  ],
  "formats": {
    "pdf": {
      "version": false,
      "index": false,
      "toc": false,
      "syntaxhighlighting": false,
      "show_comments": false
    },
    "epub": {
      "index": false,
      "toc": false,
      "epubcheck": false,
      "syntaxhighlighting": false,
      "show_comments": false
    },
    "mobi": {
      "index": false,
      "toc": false,
      "syntaxhighlighting": false,
      "show_comments": false
    },
    "html": {
      "index": false,
      "toc": false,
      "syntaxhighlighting": false,
      "show_comments": false,
      "consolidated": false
    }
  },
  "theme": "oreillymedia/jupyter_theme",
  "title": "An illustrated introduction to the t-SNE algorithm",
  "github_url": "https://github.com/oreillymedia/ipython-tutorial-content"
}